hedges/__init__.py
hedges/_version.py
hedges/bc.py
hedges/fluxes.py
hedges/hyperbolic_solver_1d.py
hedges/quadrature.py
hedges/rk.py
hedges/swe_1d/__init__.py
hedges/swe_1d/pde.py
hedges/swe_1d/steady.py
hedges-0.0.1a5.dist-info/METADATA
hedges-0.0.1a5.dist-info/WHEEL
hedges-0.0.1a5.dist-info/top_level.txt
hedges-0.0.1a5.dist-info/RECORD
