Metadata-Version: 2.1
Name: hedges
Version: 0.0.1a5
Summary: A Discontinuous Galerkin solver oriented toward prototyping and education
Author-email: schrodingersket <schrodingersket@gmail.com>
License: LGPL-2.1
Project-URL: Homepage, https://github.com/schrodingersket/hedges
Project-URL: Bug Tracker, https://github.com/schrodingersket/hedges/issues
Keywords: Partial differential equations,Hyperbolic,Scientific computing,Scientific machine learning,Discontinuous Galerkin
Classifier: Development Status :: 2 - Pre-Alpha
Classifier: License :: OSI Approved :: MIT License
Classifier: Operating System :: OS Independent
Classifier: Intended Audience :: Science/Research
Classifier: Programming Language :: Python :: 3 :: Only
Classifier: Programming Language :: Python :: 3.8
Classifier: Programming Language :: Python :: 3.9
Classifier: Programming Language :: Python :: 3.10
Classifier: Programming Language :: Python :: 3.11
Classifier: Topic :: Scientific/Engineering
Classifier: Topic :: Scientific/Engineering :: Mathematics
Classifier: Topic :: Scientific/Engineering :: Physics
Requires-Python: >=3.8
Requires-Dist: matplotlib
Requires-Dist: numpy
Requires-Dist: scipy
